heavydb/__init__.py
heavydb/_parsers.py
heavydb/_samlutils.py
heavydb/_utils.py
heavydb/connection.py
heavydb/cursor.py
heavydb/dtypes.py
heavydb/exceptions.py
heavydb/version.py
heavydb/common/__init__.py
heavydb/common/constants.py
heavydb/common/ttypes.py
heavydb/completion_hints/__init__.py
heavydb/completion_hints/constants.py
heavydb/completion_hints/ttypes.py
heavydb/extension_functions/__init__.py
heavydb/extension_functions/constants.py
heavydb/extension_functions/ttypes.py
heavydb/serialized_result_set/__init__.py
heavydb/serialized_result_set/constants.py
heavydb/serialized_result_set/ttypes.py
heavydb/thrift/Heavy-remote
heavydb/thrift/Heavy.py
heavydb/thrift/__init__.py
heavydb/thrift/constants.py
heavydb/thrift/ttypes.py
pyheavydb-6.4.0.dist-info/LICENSE.md
pyheavydb-6.4.0.dist-info/WHEEL
pyheavydb-6.4.0.dist-info/METADATA
pyheavydb-6.4.0.dist-info/RECORD
