Metadata-Version: 2.1
Name: pyheavydb
Version: 6.4.0
Summary: A DB API 2 compatible client for HeavyDB (formerly OmniSci and MapD).
Author-email: "Heavy.AI" <community@heavy.ai>
Requires-Python: >=3.7
Classifier: License :: OSI Approved :: Apache Software License
Classifier: Topic :: Database
Classifier: Topic :: Scientific/Engineering
Requires-Dist: thrift >=0.13.0
Requires-Dist: sqlalchemy >= 1.3
Requires-Dist: numpy
Requires-Dist: packaging
Requires-Dist: requests >= 2.23.0
Requires-Dist: importlib_metadata
Requires-Dist: pyheavydb[doc] ; extra == "dev"
Requires-Dist: pyheavydb[test] ; extra == "dev"
Requires-Dist: pre-commit ; extra == "dev"
Requires-Dist: flit ; extra == "dev"
Requires-Dist: sphinx ; extra == "doc"
Requires-Dist: numpydoc ; extra == "doc"
Requires-Dist: sphinx-rtd-theme ; extra == "doc"
Requires-Dist: rbc-project >=0.7.3 ; extra == "rbc"
Requires-Dist: pytest ; extra == "test"
Requires-Dist: coverage ; extra == "test"
Requires-Dist: pytest-mock ; extra == "test"
Requires-Dist: pandas ; extra == "test"
Project-URL: Home, https://github.com/heavyai/heavydb
Project-URL: Source, https://github.com/heavyai/heavydb
Provides-Extra: dev
Provides-Extra: doc
Provides-Extra: rbc
Provides-Extra: test
